{
  "development": {
    "storage": "./dev.sqlite3",
    "dialect": "sqlite"
  },
  "test": {
    "username": "root",
    "password": null,
    "database": "demo",
    "host": "localhost",
    "dialect": "mysql"
  },
  "staging": {
    "username": "gaaytsnl",
    "password": "L8CiQc-xKS5z3E_prcApjlsQOv4duMV8",
    "database": "gaaytsnl",
    "host": "arjuna.db.elephantsql.com",
    "dialect": "postgres"
  },
  "production": {
    "username": "sa",
    "password": "Tel1234!",
    "database": "CM",
    "host": "localhost",
    "port": "1113",
    "dialect": "mssql",
    "dialectOption": {
      "option": {
        "validateBulkLoadParameters": false
      }
    }
  }
}
